main.py
baseline/__init__.py
baseline/artifacts.py
baseline/assertions.py
baseline/cli.py
baseline/core.py
baseline/providers.py
baseline/runner.py
baseline_eval-0.1.7.dist-info/licenses/LICENSE
baseline_eval-0.1.7.dist-info/METADATA
baseline_eval-0.1.7.dist-info/WHEEL
baseline_eval-0.1.7.dist-info/entry_points.txt
baseline_eval-0.1.7.dist-info/top_level.txt
baseline_eval-0.1.7.dist-info/RECORD
