Metadata-Version: 2.4
Name: baseline-eval
Version: 0.1.7
Summary: Minimal, CLI-first regression testing tool for LLM prompts
Author: Wissam Al Jurdi
License:                     GNU GENERAL PUBLIC LICENSE
Project-URL: Homepage, https://github.com/waljurdi/baseline
Requires-Python: >=3.10
License-File: LICENSE
Requires-Dist: rich>=13.0.0
Requires-Dist: pyyaml>=6.0.0
Requires-Dist: ruamel.yaml>=0.17.0
Requires-Dist: jsonschema>=4.0.0
Requires-Dist: ruff>=0.14.10
Requires-Dist: types-PyYAML
Requires-Dist: pre-commit>=4.5.1
Provides-Extra: openai
Requires-Dist: openai>=1.0.0; extra == "openai"
Provides-Extra: anthropic
Requires-Dist: anthropic>=0.40.0; extra == "anthropic"
Provides-Extra: gemini
Requires-Dist: google-genai>=0.3.0; extra == "gemini"
Requires-Dist: google-generativeai>=0.8.3; extra == "gemini"
Provides-Extra: ollama
Requires-Dist: ollama>=0.3.0; extra == "ollama"
Provides-Extra: providers
Requires-Dist: openai>=1.0.0; extra == "providers"
Requires-Dist: anthropic>=0.40.0; extra == "providers"
Requires-Dist: google-genai>=0.3.0; extra == "providers"
Requires-Dist: google-generativeai>=0.8.3; extra == "providers"
Requires-Dist: ollama>=0.3.0; extra == "providers"
Provides-Extra: test
Requires-Dist: pytest>=9.0.0; extra == "test"
Provides-Extra: dev
Requires-Dist: ruff>=0.6.0; extra == "dev"
Requires-Dist: black>=24.8.0; extra == "dev"
Requires-Dist: mypy>=1.10.0; extra == "dev"
Requires-Dist: pytest>=9.0.0; extra == "dev"
Requires-Dist: types-PyYAML; extra == "dev"
Dynamic: license-file
